Workbook

Sheet Mode d'emploi
A1: Guide de remontee des anomalies - Tests metier
A3: Objectif
A4: Ce fichier sert de tableau de bord de prise en charge des anomalies : chaque colonne de l'onglet "Anomalies" existe pour eviter un aller-retour precis avec le testeur (voir le detail colonne par colonne ci-dessous). Une ligne d'exemple entierement remplie est fournie en haut de l'onglet Anomalies pour illustrer le niveau de detail attendu sur chaque champ. L'onglet "Tableau de bord" agrege automatiquement les compteurs (par statut, priorite, module) a partir des lignes saisies.
A6: Regle d'or
A7: 1 ligne = 1 anomalie. Si vous constatez plusieurs problemes distincts, meme sur le meme ecran, creez une ligne par probleme : cela evite qu'un point bloquant se retrouve fige en attente d'un autre point secondaire regroupe avec lui.
A9: Pourquoi chaque colonne existe (evite un aller-retour)
A10: Date de constat*
A11: Date reelle d'observation (pas la date de saisie du fichier) - situe l'anomalie dans le temps par rapport aux deploiements.
A12: Testeur*
A13: Nom et prenom complets. Ne pas utiliser de pseudo/code - plusieurs pseudos de la vague precedente n'ont pas pu etre decodes avec certitude.
A14: Contact
A15: Email ou telephone direct - permet de recontacter sans repasser par un intermediaire si un point precis manque.
... A58: Compteurs automatiques (formules) bases sur les colonnes Statut / Priorite / Module / Impact de l'onglet Anomalies : total de tickets, tickets bloquants encore ouverts, repartition par statut / priorite / module. Se met a jour tout seul au fur et a mesure de la saisie, aucune action manuelle requise.

Sheet Tableau de bord
A1: Tableau de bord - Suivi des anomalies
A4: Total tickets | D4: Bloquants ouverts | G4: En cours d'analyse | J4: Corriges - a valider
A5: =COUNTIF(Anomalies!A2:A1000,"?*") | D5: =COUNTIFS(Anomalies!U2:U1000,"Bloquant",Anomalies!W2:W1000,"<>Ferme - pas un bug",Anomalies!W2:W1000,"<>Corrige - a valider") | G5: =COUNTIF(Anomalies!W2:W1000,"En cours danalyse") | J5: =COUNTIF(Anomalies!W2:W1000,"Corrige - a valider")
A9: Statut | B9: Nombre | D9: Priorite | E9: Nombre | G9: Module concerne | H9: Nombre
A10: Nouveau | B10: =COUNTIF(Anomalies!W2:W1000,"Nouveau") | D10: P0 - Bloquant | E10: =COUNTIF(Anomalies!X2:X1000,"P0 - Bloquant") | G10: Ventes / Devis | H10: =COUNTIF(Anomalies!F2:F1000,"Ventes / Devis")
A11: En cours d'analyse | B11: =COUNTIF(Anomalies!W2:W1000,"En cours d'analyse") | D11: P1 | E11: =COUNTIF(Anomalies!X2:X1000,"P1") | G11: Achats | H11: =COUNTIF(Anomalies!F2:F1000,"Achats")
A12: Bug confirme | B12: =COUNTIF(Anomalies!W2:W1000,"Bug confirme") | D12: P2 | E12: =COUNTIF(Anomalies!X2:X1000,"P2") | G12: Fabrication / OF | H12: =COUNTIF(Anomalies!F2:F1000,"Fabrication / OF")
A13: Corrige - a valider | B13: =COUNTIF(Anomalies!W2:W1000,"Corrige - a valider") | D13: Differe | E13: =COUNTIF(Anomalies!X2:X1000,"Differe") | G13: Atelier | H13: =COUNTIF(Anomalies!F2:F1000,"Atelier")
A14: Ferme - pas un bug | B14: =COUNTIF(Anomalies!W2:W1000,"Ferme - pas un bug") | G14: Stock / Livraison | H14: =COUNTIF(Anomalies!F2:F1000,"Stock / Livraison")
A15: Standby / arbitrage requis | B15: =COUNTIF(Anomalies!W2:W1000,"Standby / arbitrage requis") | G15: Facturation | H15: =COUNTIF(Anomalies!F2:F1000,"Facturation")
A16: Transfere a un tiers | B16: =COUNTIF(Anomalies!W2:W1000,"Transfere a un tiers") | G16: RH / Conges | H16: =COUNTIF(Anomalies!F2:F1000,"RH / Conges")
G17: Contacts / CRM | H17: =COUNTIF(Anomalies!F2:F1000,"Contacts / CRM")
G18: Planification / Capacite | H18: =COUNTIF(Anomalies!F2:F1000,"Planification / Capacite")
G19: Autre | H19: =COUNTIF(Anomalies!F2:F1000,"Autre")
A21: Ces compteurs se mettent a jour automatiquement des qu'une ligne est ajoutee/modifiee dans l'onglet Anomalies.

Sheet Anomalies
A1: N* ticket | B1: Date de constat* | C1: Testeur (nom complet)* | D1: Contact (email/tel) | E1: Environnement* | F1: Module concerne* | G1: Ecran / Menu exact* | H1: URL Odoo (lien direct)* | I1: Type d'enregistrement | J1: Reference enregistrement (N*) | K1: Constate* | L1: Attendu* | M1: Chemin de reproduction* | N1: Donnees de test utilisees | O1: Message d'erreur exact | P1: Ca fonctionnait avant ? | Q1: Frequence* | R1: Navigateur / poste | S1: Capture d'ecran jointe* | T1: Lien / nom fichier capture | U1: Impact metier percu* | V1: Commentaire libre | W1: Statut | X1: Priorite arbitree | Y1: Responsable | Z1: Date de prise en charge | AA1: Version corrigee / commit | AB1: Valide par metier
A2: T-01 | B2: 15/07/2026 | C2: Valentin Lemonnier | F2: Ventes / Devis | G2: Ventes > Devis > formulaire (champs Gamme / Serie) | I2: Devis | K2: Pas de champ Gamme ni Serie visible sur le devis ; une fois ajoutes, la liste deroulante de Serie proposait toutes les series, pas seulement celles de la bonne Gamme | L2: Champs Gamme et Serie visibles, liste de Serie filtree selon la Gamme selectionnee (relation x_serie_mtn -> x_studio_gamme_de_la_srie) | P2: Non - nouveau probleme (champs jamais affiches) | U2: Genant | V2: Domaine ajoute au champ Serie (commit c4c77e9), validation metier du 17/07 confirmee dans le code | W2: Corrige - a valider | X2: P1 | Y2: JBS | Z2: 20/07/2026 | AA2: fma_sale_order_custom 19.0.1.0.4 ; domaine commit c4c77e9 | AB2: Oui
A3: T-02 | B3: 15/07/2026 | C3: Valentin Lemonnier | F3: Ventes / Devis | G3: Ventes > Devis / Affaire (selection du client) | I3: Devis | K3: Le commercial ne s'affecte pas automatiquement a la selection du client (fonctionne uniquement pour Commercial SI prospect) | L3: Commercial auto-rempli depuis le commercial parametre sur la fiche client | P3: Oui - regression | U3: Genant | V3: Retest Nolhan + Valentin : fonctionnait en pratique dans certains cas ; un champ Employe a neanmoins ete recree sur contact/Affaire/devis pour fiabiliser | W3: Corrige - a valider | X3: P1 | Y3: JBS / DAVSOR | Z3: 20/07/2026
A4: T-03 | B4: 15/07/2026 | C4: Valentin Lemonnier | F4: Ventes / Devis | G4: Affaire (mode de reglement / condition de paiement) | I4: Affaire | K4: Le mode de reglement ne se renseigne pas automatiquement depuis le client | L4: Le champ standard 'Condition de paiement' doit se recuperer depuis la fiche client sur l'Affaire | P4: Oui - regression | U4: Genant | V4: 4 champs 'mode de reglement' coexistaient, source de confusion ; champ recree directement sur l'Affaire suite a l'arbitrage en reunion | W4: Corrige - a valider | X4: P1 | Y4: JBS / DAVSOR | Z4: 20/07/2026
A5: T-04 | B5: 15/07/2026 | C5: Valentin Lemonnier | E5: Pre-production | F5: Ventes / Devis | G5: Affaire (chatter) / bloc Chronologie du devis | I5: Affaire | K5: Chronologie/chatter affaire pas positionne a droite comme en production | L5: Meme agencement qu'en production | S5: Oui - lien ci-dessous | T5: Captures prod vs pre-prod utilisees en reunion du 20/07 (non re-jointes dans ce fichier) | U5: Amelioration souhaitee | V5: Chatter : comportement responsive standard d'Odoo 19 (bascule a droite au-dela de ~1920px), pas un bug. Distinct du bloc Chronologie du devis, retravaille en plusieurs iterations suite aux captures d'ecran (commits 022d964 / 9a94f76) | W5: Ferme - pas un bug | X5: Differe | Z5: 20/07/2026 | AB5: Oui
A6: T-05 | B6: 15/07/2026 | C6: Valentin Lemonnier | F6: Ventes / Devis | G6: Affaire (x_affaire) | I6: Affaire | K6: Le champ affiche 'Projet' devrait s'appeler 'Compte analytique' | L6: Champ 'Compte analytique' present sur l'Affaire (verifie en code : n'existe pas du tout aujourd'hui, pas un simple probleme d'etiquette) | P6: Non - nouveau probleme | U6: Amelioration souhaitee | V6: Mis en pause : fusion Projet / Compte analytique / Projet MTN en cours de cadrage, a ne pas traiter isolement | W6: Standby / arbitrage requis | X6: Differe | Y6: David / JBS | Z6: 20/07/2026
A7: T-06 | B7: 15/07/2026 | C7: Valentin Lemonnier | F7: Ventes / Devis | G7: Affaire / Projet MTN (workflow chef de projet / technicien BE) | I7: Affaire | K7: Le champ 'BE' se remplit alors qu'il devrait rester vide tant que le projet n'est pas valide | L7: Champ BE vide jusqu'a 'Devis valide le', rempli ensuite via le Chef de projet | U7: Amelioration souhaitee | V7: Ferme explicitement par le testeur en reunion : comportement confirme correct en v19 | W7: Ferme - pas un bug | Z7: 20/07/2026 | AB7: Oui
A8: T-07 | B8: 15/07/2026 | C8: Valentin Lemonnier | F8: Contacts / CRM | G8: Contacts (vue Kanban) | I8: Contact | K8: Preference pour l'ancien module Contact ; souhait de distinguer visuellement client / adresse chantier / contact | L8: Badge visuel Client/Chantier/Contact directement dans la vue Kanban | U8: Amelioration souhaitee | V8: Devient une vraie demande d'evolution ; confirme en reunion comme un changement d'ergonomie standard Odoo 19, sans lien avec la migration | W8: Standby / arbitrage requis | X8: Differe | Y8: JBS | Z8: 20/07/2026
A9: T-08 | B9: 15/07/2026 | C9: Valentin Lemonnier | D9: Utilisateur reellement impacte : Nolhan Pavin (nolhan.pavin@janneau.com) | E9: Pre-production | F9: Autre | G9: Tableau de bord Spreadsheet 'Ventes FMA' (menu Ventes) | I9: Autre / sans objet | K9: Le dashboard 'Ventes FMA' affiche un contenu generique au lieu du rapport detaille attendu (fonctionne pour F2M) | L9: Le dashboard 'Ventes FMA' doit afficher le rapport detaille (Devis realises, prise de commande, taux de transformation) | N9: Compte Nolhan Pavin (id=69) ; spreadsheet.dashboard id=12 'Ventes FMA' vs id=64 'Ventes FMA (2025)' | S9: Oui - lien ci-dessous | T9: Captures prod vs pre-prod utilisees le 20/07 (non re-jointes dans ce fichier) | U9: Genant | V9: Confirme en test direct le 21/07 (backup pre-prod du jour, connexion reelle) : pas un bug de code, probleme de nommage - le rapport detaille existe mais range sous 'Ventes FMA (2025)' au lieu de 'Ventes FMA'. Action requise : renommer/reorganiser les dashboards directement en production (donnee, hors code) | W9: En cours d'analyse | X9: P2 | Y9: JBS / Alexis | Z9: 20/07/2026
A10: T-09 | B10: 15/07/2026 | C10: Elowen Gauthier | F10: Ventes / Devis | G10: Affaire > Onglet Autres informations | I10: Affaire | K10: Champ 'Dates effective' manquant | L10: Date a laquelle la livraison est totalement effectuee | U10: Amelioration souhaitee | V10: Clarifie par le testeur ; reste a trancher si le champ doit etre calcule automatiquement (derniere livraison liee) ou saisi manuellement - pas de developpement engage | W10: Ferme - pas un bug | Z10: 20/07/2026 | AB10: Oui
A11: T-10 | B11: 15/07/2026 | C11: Elowen Gauthier | F11: Fabrication / OF | G11: Ordre de fabrication > Onglet Ordre de travail | I11: Ordre de fabrication | K11: Colonne 'sequence operation' invisible/absente | L11: Colonne toujours visible, triee par ordre chronologique, comme en production | P11: Oui - regression | U11: Genant | V11: Corrige : poignee de tri en brouillon uniquement, valeur en lecture seule ensuite - confirme par le testeur | W11: Corrige - a valider | X11: P1 | Y11: JBS | Z11: 20/07/2026 | AA11: mrp_capacity_planning 19.0.1.0.6 | AB11: Oui
A12: T-11 | B12: 15/07/2026 | C12: Elowen Gauthier | F12: Fabrication / OF | G12: Ordre de fabrication > Onglet Divers | I12: Ordre de fabrication | K12: Le projet ne se renseigne pas automatiquement sur l'onglet Divers | L12: Projet renseigne automatiquement depuis le devis d'origine | U12: Genant | V12: Retour ambigu ('sur les anciennes commandes ca marche') ; rouvert en reunion faute de confirmation ferme - a retester specifiquement sur des affaires/commandes creees apres la migration | W12: Standby / arbitrage requis | X12: P2 | Y12: JBS | Z12: 20/07/2026
A13: T-12 | B13: 15/07/2026 | C13: Elowen Gauthier | F13: Achats | G13: Commande d'achat (en-tete) | I13: Commande d'achat | J13: P27214 | K13: 'Projet du SO' vide, 'Is XML Created' absent de la fiche (visible seulement en liste), commentaires livraison/interne absents | L13: Champs en en-tete (pas de duplication par ligne), 'Projet du SO' propage automatiquement depuis le devis source | N13: Commande P27214 (test de propagation reussi) | P13: Non - nouveau probleme | U13: Bloquant | V13: Confirme une seconde fois independamment (81 commandes sur 169 avaient 'Projet du SO' vide en base, soit 48%). Corrige le 21/07 par propagation automatique a la creation/ecriture (ne touche jamais une saisie manuelle existante) ; rattrapage sur 93 commandes existantes fait en local, a rejouer en production apres deploiement | W13: Corrige - a valider | X13: P0 - Bloquant | Y13: JBS | Z13: 20/07/2026 | AA13: custom 19.0.1.0.18, commit 476c639
A14: T-13 | B14: 15/07/2026 | C14: Elowen Gauthier | F14: Achats | G14: Commande d'achat vitrage (categorie Remplissage) | I14: Commande d'achat | K14: Champs manquants : remise, commentaire livraison, dimensions, hauteur/largeur, repartition analytique qui ne se propage pas ; 'Contrat cadre' affiche a tort | L14: Champs vitrage affiches uniquement sur les commandes concernees (categorie Remplissage), Contrat cadre masque | P14: Non - nouveau probleme | U14: Genant | V14: Confirme independamment par 3 remontees supplementaires (onglet vitrage manquant, remise fournisseur, analytique par ligne - voir T-26/T-27). Corrige : champ calcule x_is_glazing_order conditionne l'affichage remise/commentaires/dimensions ; Contrat cadre masque sur toutes les commandes. Repartition analytique automatique en standby (David) | W14: Corrige - a valider | X14: P1 | Y14: JBS / David | Z14: 20/07/2026 | AA14: custom 19.0.1.0.15
A15: T-14 | B15: 15/07/2026 | C15: Mathieu Angibault | F15: Ventes / Devis | G15: Ventes > Affaire > Nouveau | I15: Affaire | K15: Impossible de creer une Affaire (droit manquant) | L15: Creation d'Affaire possible pour un profil commercial standard | N15: Compte Mathieu Angibault, test direct via Ventes > Affaire > Nouveau > Enregistrer | P15: Oui - regression | U15: Bloquant | V15: Corrige (ajout au groupe 'Utilisateur interne'), confirme en test direct le 17/07 en se connectant avec le compte de Mathieu. Reste a faire : confirmation finale par Mathieu lui-meme avec son propre mot de passe ; supprimer l'enregistrement de test x_affaire id=4093 | W15: Corrige - a valider | X15: P0 - Bloquant | Y15: JBS | Z15: 16/07/2026 | AB15: Oui
A16: T-15 | B16: 16/07/2026 | C16: Emilien Davoine | F16: Planification / Capacite | G16: Planification capacite (vue Gantt hebdomadaire) | I16: Autre / sans objet | K16: Un conge d'1 jour retire la capacite de toute la semaine au lieu du seul jour concerne | L16: Seule la journee en conge doit voir sa capacite reduite | N16: Conge Jessica PETIT du 19/06/2026 (~5h10, Compensatory Days) : calcul manuel = 5.0h (correct), valeur stockee en base = 0.0h (fausse) | U16: Bloquant | V16: Confirme reellement faux (pas juste visuel). Cause : champ calcule stocke ne pouvant dependre directement d'une recherche sur les conges (limite structurelle Odoo) ; le cron quotidien ne recalculait jamais les semaines deja passees. Corrige : recalcul immediat a la creation/modification/suppression d'un conge + cron elargi (30 derniers jours) | W16: Corrige - a valider | X16: P0 - Bloquant | Y16: JBS | Z16: 20/07/2026 | AA16: mrp_capacity_planning 19.0.1.0.7 | AB16: Oui
A17: T-16 | B17: 16/07/2026 | C17: Emilien Davoine | F17: Fabrication / OF | G17: Ordre de fabrication (formulaire) | I17: Ordre de fabrication | K17: Champ 'Niveau de complexite' absent de la vue formulaire de l'OF | L17: Champ visible et modifiable sur l'OF | P17: Non - nouveau probleme | U17: Genant | V17: Champ deja securise en code, ajoute a la vue formulaire ; refonte propre prevue post-v19 (Logical/Tech Design) | W17: Corrige - a valider | X17: P2 | Y17: JBS | Z17: 20/07/2026 | AA17: custom 19.0.1.0.11 | AB17: Oui
A18: T-17 | B18: 16/07/2026 | C18: Emilien Davoine | F18: Fabrication / OF | G18: Ordre de fabrication (acces aux PO lies) | I18: Ordre de fabrication | K18: Les commandes d'achat liees a l'OF ne sont plus accessibles depuis l'OF | L18: Acces aux PO lies depuis la fiche OF (smart-button ou equivalent) | P18: Oui - regression | U18: Genant | V18: Corrige uniquement dans le popup de replanification (commits du 13/07). Un smart-button 'Achats' standard existe deja nativement (module purchase_mrp) mais ne remonte pas les PO crees manuellement hors chaine d'approvisionnement. David reprend le sujet avec Jean | W18: Bug confirme | X18: P2 | Y18: David | Z18: 20/07/2026
A19: T-18 | B19: 16/07/2026 | C19: Emilien Davoine | F19: Planification / Capacite | G19: Menu 'Capacite par poste' | I19: Autre / sans objet | K19: Pas d'acces a l'ecran 'Capacite par poste' (erreur au chargement) | L19: Ecran accessible pour un profil utilisateur standard | O19: OwlError / this.child.mount is not a function | U19: Bloquant | V19: Droits verifies corrects (base.group_user, lecture/ecriture/creation), action et vue conformes, rien ne reproduit le crash cote serveur avec le contexte exact d'Emilien. Hypothese cache navigateur confirmee le 21/07 par test en navigateur entierement neuf (aucun cache/cookie) : ecran fonctionne parfaitement, 9 postes affiches, aucune erreur. Pas un bug de code ni de droits | W19: Ferme - pas un bug | Y19: JBS | Z19: 20/07/2026 | AB19: Oui
A20: T-19 | B20: 16/07/2026 | C20: Emilien Davoine | F20: Fabrication / OF | G20: Ordre de fabrication > Onglet Ordre de travail | I20: Ordre de fabrication | K20: Modification des heures prevues (duration_expected) impossible directement en ligne | L20: Champ modifiable en ligne comme avant | U20: Genant | V20: Ferme en reunion : comportement standard v19 (readonly seulement si etat annule/termine), a traiter par le process plutot que le code. Teste en direct le 21/07 sur un OT reel en etat 'Pret' : ecriture reussie sans blocage - toujours besoin d'un OF + etat precis si le probleme se reproduit | W20: Ferme - pas un bug | Z20: 20/07/2026 | AB20: Oui
A21: T-20 | B21: 16/07/2026 | C21: Emilien Davoine | F21: Planification / Capacite | G21: Capacite par poste (ex. Montage) | I21: Autre / sans objet | K21: 80,1h / 3 ressources : le planning se fait avec une seule ressource au lieu de repartir sur les 3 | L21: Reservation multi-ressources reelle | N21: Poste Montage, seuil 80,1h | P21: Non - meme comportement en v17, pas une regression (limite structurelle pre-existante) | U21: Genant | V21: Confirme : le nombre de ressources ne fait que raccourcir la duree affichee, sans reservation multi-ressources reelle. Correctif ponctuel fait : champs Duree mini/maxi passes de Entier a Decimal (un seuil comme 80,1h etait tronque a 80, faussant le comparateur >80h). Point restant a surveiller : recalcul des jours planifies apres replanification | W21: Corrige - a valider | X21: P2 | Y21: JBS | Z21: 20/07/2026 | AA21: fma_studio_models 19.0.1.0.13
A22: T-21 | B22: 16/07/2026 | C22: Emilien Davoine | F22: Autre | G22: Filtres personnalises / modeles d'export Excel (plusieurs modules) | I22: Autre / sans objet | K22: Craint que les filtres et exports personnalises soient perdus | L22: Filtres et exports conserves apres migration | U22: Amelioration souhaitee | V22: ir.filters et ir.exports sont des donnees utilisateur en base, non versionnees dans le code - hors perimetre dev. A verifier/sauvegarder directement en base (staging vers prod) | W22: Ferme - pas un bug | Z22: 20/07/2026
A23: T-22 | B23: 16/07/2026 | C23: Emilien Davoine | F23: Stock / Livraison | G23: Ecran de reception via douchette code-barres | I23: Livraison / Transfert | K23: Impossible d'acceder au mouvement de transfert via code-barres | L23: Ajouter le Numero de BL a l'ecran de reception code-barres | P23: Non - nouveau probleme | U23: Bloquant | V23: stock_barcode (Enterprise) installe mais base sur des composants JS/Owl (pas de vues XML classiques) - ajouter un champ demande une surcharge JS d'un outil utilise quotidiennement par les operateurs. En attente de confirmation Emilien/David sur le champ backend cible (origin existant vs nouveau champ dedie) avant de developper, pour ne pas risquer de casser un outil critique | W23: Standby / arbitrage requis | X23: P1 | Y23: JBS | Z23: 20/07/2026
A24: T-23 | B24: 17/07/2026 | C24: Emilien Davoine | F24: Achats | G24: Reception fournisseur > Creation Facture Fournisseur en masse | I24: Commande d'achat | K24: La facture creee sur reception reste en brouillon (attendait une validation automatique) | L24: A clarifier : validation automatique de la facture attendue ? | P24: Non - comportement standard Odoo, jamais d'auto-validation, portage fidele | U24: Amelioration souhaitee | V24: Le bouton action_create_supplier_invoices plantait systematiquement avant le correctif du bug critique fma_custom/models (voir T-30) - n'avait jamais pu etre valide en conditions reelles avant le 21/07. A retester maintenant que le bouton fonctionne, pour clarifier s'il s'agit d'une vraie demande de redeveloppement | W24: Bug confirme | X24: P2 | Y24: David | Z24: 20/07/2026
A25: T-24 | B25: 17/07/2026 | C25: Emilien Davoine | F25: Fabrication / OF | G25: Module Atelier (ecran non localise) | I25: Autre / sans objet | K25: Composants manquants affiches sous une etiquette 'Affaire' peu lisible | L25: Etiquette lisible / ecran clarifie | U25: Amelioration souhaitee | V25: Ecran exact non localise dans fma_atelier (aucune logique de composants manquants trouvee). Le symptome ('etiquette peu lisible') correspond au bug systemique _rec_name deja corrige (voir T-31) - probablement deja resolu par ce correctif meme sans avoir localise l'ecran exact. Differe, non prioritaire | W25: Standby / arbitrage requis | X25: Differe | Y25: JBS | Z25: 20/07/2026
A26: T-25 | C26: CLEGIS (nom non decode) | F26: Achats | G26: Commande d'achat (champ Reference) | I26: Commande d'achat | K26: Champ Reference non renseigne sur un cas precis | L26: A verifier sur le cas precis signale (lien de la commande transmis en reunion) | U26: Amelioration souhaitee | V26: Clarifie : le champ se renseigne par defaut avec les initiales de l'utilisateur connecte, modifiable manuellement - fonctionnement confirme. Le lien vers la commande concernee evoque en reunion n'a jamais ete transmis pour verification ciblee | W26: Standby / arbitrage requis | X26: P2 | Z26: 20/07/2026
A27: T-26 | C27: CLEGIS (nom non decode) | F27: Achats | G27: Commande d'achat vitrage | I27: Commande d'achat | K27: La remise fournisseur n'apparait pas | L27: Champ remise visible sur la commande | P27: Non - nouveau probleme | U27: Genant | V27: Rejoint T-13 : champ expose via le meme correctif (x_is_glazing_order). Auto-application du taux de remise en standby | W27: Corrige - a valider | X27: P2 | Y27: JBS | Z27: 20/07/2026 | AA27: custom 19.0.1.0.15
A28: T-27 | C28: CLEGIS (nom non decode) | F28: Achats | G28: Export analytique par ligne | I28: Commande d'achat | K28: Analytique par ligne non renseigne a l'export | L28: A preciser | U28: Genant | V28: Standby, David travaille le sujet separement (repartition analytique depuis le Projet du SO) | W28: Standby / arbitrage requis | X28: Differe | Y28: David | Z28: 20/07/2026
A29: T-28 | C29: CLEGIS (nom non decode) | F29: Stock / Livraison | G29: Transfert de livraison, site LA REGRIPPIERE (LRE-Prefabrication) | I29: Livraison / Transfert | K29: 2 onglets affiches sur l'ecran de livraison, un seul attendu | L29: 1 seul onglet | N29: Picking type 'Collecter les composants' (LA REGRIPPIERE id=28, 8388 transferts ; LA REMAUDIERE id=34, 1748 transferts) | S29: Non | U29: Genant | V29: Picking type candidat identifie ; ecran exact ou apparaissent les '2 onglets' non localise dans le code (probablement un ecran standard Odoo Inventaire sans personnalisation FMA). Mis de cote a la demande de l'utilisateur plutot que de deviner l'ecran - capture d'ecran necessaire pour trancher | W29: Standby / arbitrage requis | X29: P2 | Y29: JBS | Z29: 20/07/2026
A30: T-29 | C30: Emilien Davoine | F30: Achats | G30: Renvoi manuel XML SFTP | I30: Commande d'achat | K30: Le renvoi manuel du XML par SFTP est bloque | L30: Bouton/action de renvoi manuel fonctionnel | U30: Genant | V30: Nouvelle demande confirmee en reunion, pas d'action JBS - David en responsable | W30: Nouveau | X30: P2 | Y30: David | Z30: 20/07/2026
A31: T-30 | B31: 21/07/2026 | F31: Achats | G31: Actions utilisant fma_custom (menu Actions > 'Fichier clients Iziqo', 'Creation Facture Fournisseur en masse') | I31: Autre / sans objet | K31: fma_custom/__init__.py n'importait que 'wizard', jamais 'models' : les 6 fichiers de fma_custom/models/ n'etaient jamais charges dans le registre ORM malgre le module marque installe | L31: Les modeles de fma_custom doivent etre charges et actifs | O31: AttributeError sur res.partner.action_export_iziqo_customers et stock.picking.action_create_supplier_invoices | P31: Oui - regression silencieuse (jamais fonctionnel depuis le portage, masque par les automatisations Studio encore actives) | U31: Bloquant | V31: Decouverte critique du 21/07/2026 en reprenant un point non resolu. 2 actions cliquables reelles plantaient pour quiconque cliquait dessus (voir T-23) ; un cron desactive par defaut aurait aussi plante s'il avait ete active. Point de vigilance : reactive aussi une propagation analytique deja geree par l'automatisation Studio equivalente (calcul redondant mais idempotent, pas de risque de double ecriture) | W31: Corrige - a valider | X31: P0 - Bloquant | Y31: JBS | Z31: 21/07/2026 | AA31: fma_custom 19.0.1.0.4, commit 476c639
A32: T-31 | B32: 17/07/2026 | F32: Autre | G32: Listes deroulantes / champs lies referencant un modele Studio (Affaire, Gamme, Serie, Capacite par poste, Reglements...) | I32: Autre / sans objet | K32: Valeurs affichees au format technique 'x_affaire_stage,1' au lieu du nom reel | L32: Nom lisible de l'enregistrement affiche partout | P32: Non - nouveau probleme (aucun des 20 modeles portes depuis Studio ne declarait _rec_name) | U32: Genant | V32: Decouvert en testant T-14 (droit affaire). Affecte potentiellement toutes les listes deroulantes et champs lies vers un x_affaire/x_gamme_mtn/x_serie_mtn/x_capacite_par_poste/x_reglements etc. dans toute l'application. Pourrait expliquer une partie de la confusion Projet/Affaire remontee ailleurs (T-05, T-11) | W32: Corrige - a valider | X32: P1 | Y32: JBS | Z32: 17/07/2026 | AA32: fma_studio_models 19.0.1.0.9
A33: T-32 | B33: 17/07/2026 | F33: Autre | G33: Listes deroulantes Gamme / Serie / Etape affaire / Remises et autres modeles Studio | I33: Autre / sans objet | K33: Valeurs affichees comme un dictionnaire de traduction brut, ex. {'en_US': 'Forster', 'fr_FR': 'Forster'} au lieu de 'Forster' | L33: Valeur traduite affichee normalement | P33: Non - nouveau probleme (13 des 20 modeles ont x_name stocke en jsonb en base mais declare comme Char simple en Python, sans translate=True) | U33: Genant | V33: Decouvert en retestant T-01 (Gamme/Serie). 16 champs concernes sur 9 modeles (x_affaire_stage, x_capacite_par_poste, x_delai_entre_operatio, x_gamme_mtn, x_serie_mtn, x_reglements, famille x_remise, etc.). x_affaire lui-meme non concerne (deja en character varying). Se cumulait avec T-31 sur l'ecran Etape d'affaire | W33: Corrige - a valider | X33: P1 | Y33: JBS | Z33: 17/07/2026 | AA33: fma_studio_models 19.0.1.0.10
A34: T-33 | B34: 17/07/2026 | C34: Non attribue (probablement Elowen Gauthier) | F34: Achats | G34: Import fournisseurs (flux AllArticles, sqlite_connector) | I34: Commande d'achat | K34: Delais de reception de bon de commande mal estimes par Odoo | L34: Delai fournisseur reel repris depuis la source d'import | U34: Genant | V34: Bug de code reel localise : sqlite_connector.py ligne 516 initialise delai=0 avant la boucle d'import AllArticles et ne le reaffecte jamais avant utilisation (ligne 675, product.supplierinfo.delay). Tout fournisseur importe via ce flux se retrouve avec un delai fige a 0 jour. Correctif impossible sans info externe : la requete SQL ne remonte aucune colonne de delai - besoin du schema source (quelle colonne d'AllArticles contient le vrai delai) ou d'une regle metier de valeur par defaut | W34: Standby / arbitrage requis | X34: P1 | Y34: JBS | Z34: 21/07/2026
A35: T-34 | B35: 17/07/2026 | C35: Non attribue (probablement Elowen Gauthier) | F35: Achats | G35: Reglages > Technique > Sequences (purchase.order) | I35: Commande d'achat | J35: P27214 | K35: Numeros de commandes non generes | L35: Sequence purchase.order fonctionnelle | N35: 27214 commandes existantes, derniere P27214 | U35: Bloquant | V35: Aucun bug de code trouve (sequence standard non redefinie). Verifie en base le 21/07 : ir_sequence pour purchase.order avait number_next=1 malgre 27214 commandes deja creees - le prochain achat aurait ete numerote P1. Corrige dans la base de test locale (number_next -> 27215). Pas un bug de code : la meme verification est a faire en production, ou le meme probleme est susceptible d'exister | W35: Bug confirme | X35: P0 - Bloquant | Y35: JBS | Z35: 21/07/2026
A36: T-35 | B36: 17/07/2026 | C36: Non attribue (probablement Elowen Gauthier) | F36: Achats | G36: Export PO format Comalu (SFTP) | I36: Commande d'achat | J36: P05545 | K36: Lignes XML manquantes a l'export d'une commande au format Comalu | L36: Toutes les lignes pertinentes doivent apparaitre dans le XML | N36: Commande P05545 (55 lignes), contient une ligne avec default_code='affaire' | U36: Genant | V36: Piste technique solide confirmee sur donnees reelles le 21/07 : le template d'export Comalu (et TIV, meme filtre) exclut silencieusement toute ligne dont le produit a pour reference interne exactement 'affaire'. Decision metier a prendre : filtre volontaire (lignes internes a ne jamais envoyer au fournisseur) ou a ajuster ? | W36: Standby / arbitrage requis | X36: P1 | Y36: JBS | Z36: 21/07/2026

Sheet Suivi des echanges
A1: N* ticket | B1: Date | C1: Auteur | D1: Message / echange | E1: Nouveau statut (optionnel)
A2: T-28 | B2: 15/07/2026 | C2: CLEGIS | D2: Signalement initial : 2 onglets affiches sur l'ecran de livraison LRE-Prefabrication. | E2: Nouveau
A3: T-28 | B3: 20/07/2026 | C3: JBS | D3: Investigation en cours, picking type candidat identifie (Collecter les composants) ; mis en standby faute d'ecran exact confirme - capture d'ecran demandee. | E3: Standby / arbitrage requis
